MANIFEST.in
README.rst
screenshot.png
setup.py
docs/HISTORY.txt
plonetheme/__init__.py
plonetheme.ploneorg.egg-info/PKG-INFO
plonetheme.ploneorg.egg-info/SOURCES.txt
plonetheme.ploneorg.egg-info/dependency_links.txt
plonetheme.ploneorg.egg-info/entry_points.txt
plonetheme.ploneorg.egg-info/namespace_packages.txt
plonetheme.ploneorg.egg-info/not-zip-safe
plonetheme.ploneorg.egg-info/requires.txt
plonetheme.ploneorg.egg-info/top_level.txt
plonetheme/ploneorg/__init__.py
plonetheme/ploneorg/configure.zcml
plonetheme/ploneorg/tests.py
plonetheme/ploneorg/theme/ploneorg/manifest.cfg
plonetheme/ploneorg/theme/ploneorg/rules.xml
plonetheme/ploneorg/theme/ploneorg/screenshot.png
plonetheme/ploneorg/theme/ploneorg/theme.html
plonetheme/ploneorg/theme/ploneorg/wide.html
plonetheme/ploneorg/theme/ploneorg/static/css/ie.css
plonetheme/ploneorg/theme/ploneorg/static/css/plone-trac.css
plonetheme/ploneorg/theme/ploneorg/static/css/plone.css
plonetheme/ploneorg/theme/ploneorg/static/css/theme.css
plonetheme/ploneorg/theme/ploneorg/static/images/arrow-blue.png
plonetheme/ploneorg/theme/ploneorg/static/images/arrow-white.png
plonetheme/ploneorg/theme/ploneorg/static/images/box-gradient.png
plonetheme/ploneorg/theme/ploneorg/static/images/cogs.png
plonetheme/ploneorg/theme/ploneorg/static/images/conferences-wpd.png
plonetheme/ploneorg/theme/ploneorg/static/images/conferences.png
plonetheme/ploneorg/theme/ploneorg/static/images/download-box.png
plonetheme/ploneorg/theme/ploneorg/static/images/download-platforms.png
plonetheme/ploneorg/theme/ploneorg/static/images/footer-gradient.png
plonetheme/ploneorg/theme/ploneorg/static/images/footer-logo.png
plonetheme/ploneorg/theme/ploneorg/static/images/frontpage-image.png
plonetheme/ploneorg/theme/ploneorg/static/images/frontpage-image2.jpg
plonetheme/ploneorg/theme/ploneorg/static/images/frontpage-image3.jpg
plonetheme/ploneorg/theme/ploneorg/static/images/nav-gradient.png
plonetheme/ploneorg/theme/ploneorg/static/images/nav_bg.png
plonetheme/ploneorg/theme/ploneorg/static/images/plone-icon-24-selected.png
plonetheme/ploneorg/theme/ploneorg/static/images/plone-icon-24.png
plonetheme/ploneorg/theme/ploneorg/static/images/plone-logo-24.png
plonetheme/ploneorg/theme/ploneorg/static/images/plone-logo-56.png
plonetheme/ploneorg/theme/ploneorg/static/images/search-wrapper.png
