Metadata-Version: 1.1
Name: plonetheme.ploneorg
Version: 0.0.5
Summary: Plone.org theme
Home-page: https://github.com/plone/plonetheme.ploneorg
Author: Alex Clark
Author-email: aclark@aclark.net
License: GPL2
Keywords: plone theme zope
Platform: UNKNOWN
Classifier: Framework :: Plone
Classifier: Framework :: Plone :: 4.3
Classifier: Programming Language :: Python :: 2.7
Classifier: Programming Language :: Python :: 2 :: Only
